kombucha/__init__.py
kombucha-0.1.dist-info/DESCRIPTION.rst
kombucha-0.1.dist-info/METADATA
kombucha-0.1.dist-info/RECORD
kombucha-0.1.dist-info/WHEEL
kombucha-0.1.dist-info/metadata.json
kombucha-0.1.dist-info/top_level.txt
