Metadata-Version: 2.0
Name: kombucha
Version: 0.1
Summary: Drink a dict
Home-page: https://github.com/eL0ck/Kombucha
Author: eL0ck
Author-email: tpj800@gmail.com
License: MIT
Platform: UNKNOWN
